calibration_client/__init__.py
calibration_client/calibration_client.py
calibration_client/calibration_client_api.py
calibration_client/apis/__init__.py
calibration_client/apis/calibration_api.py
calibration_client/apis/calibration_constant_api.py
calibration_client/apis/calibration_constant_version_api.py
calibration_client/apis/condition_api.py
calibration_client/apis/detector_api.py
calibration_client/apis/detector_type_api.py
calibration_client/apis/parameter_api.py
calibration_client/apis/physical_detector_unit_api.py
calibration_client/apis/report_api.py
calibration_client/apis/user_api.py
calibration_client/common/__init__.py
calibration_client/common/base.py
calibration_client/common/config.py
calibration_client/common/util.py
calibration_client/modules/__init__.py
calibration_client/modules/calibration.py
calibration_client/modules/calibration_constant.py
calibration_client/modules/calibration_constant_version.py
calibration_client/modules/condition.py
calibration_client/modules/detector.py
calibration_client/modules/detector_type.py
calibration_client/modules/parameter.py
calibration_client/modules/physical_detector_unit.py
calibration_client/modules/report.py
calibration_client/tests/__init__.py
calibration_client/tests/calibration_client_by_detector_test.py
calibration_client/tests/calibration_client_test.py
calibration_client/tests/calibration_test_hash.py
calibration_client/tests/conftest.py
calibration_client/tests/apis/__init__.py
calibration_client/tests/apis/api_base.py
calibration_client/tests/apis/calibration_api_test.py
calibration_client/tests/apis/calibration_constant_api_test.py
calibration_client/tests/apis/calibration_constant_version_api_test.py
calibration_client/tests/apis/condition_api_test.py
calibration_client/tests/apis/detector_api_test.py
calibration_client/tests/apis/detector_type_api_test.py
calibration_client/tests/apis/parameter_api_test.py
calibration_client/tests/apis/physical_detector_unit_api_test.py
calibration_client-11.4.0.dist-info/AUTHORS.rst
calibration_client-11.4.0.dist-info/LICENSE
calibration_client-11.4.0.dist-info/METADATA
calibration_client-11.4.0.dist-info/WHEEL
calibration_client-11.4.0.dist-info/top_level.txt
calibration_client-11.4.0.dist-info/RECORD
