Metadata-Version: 2.1
Name: calibration-client
Version: 11.4.0
Summary: Python Client for European XFEL Calibration Catalogue Web App available at https://in.xfel.eu/calibration
Home-page: https://git.xfel.eu/ITDM/calibration_client
Author: Luís Maia
Author-email: luis.maia@xfel.eu
Maintainer: Luís Maia
Maintainer-email: luis.maia@xfel.eu
License: MIT
Platform: any
Classifier: Development Status :: 5 - Production/Stable
Classifier: Environment :: Web Environment
Classifier: Environment :: Console
Classifier: Intended Audience :: Developers
Classifier: Intended Audience :: Science/Research
Classifier: Natural Language :: English
Classifier: License :: OSI Approved :: MIT License
Classifier: Programming Language :: Python
Classifier: Programming Language :: Python :: 3
Classifier: Operating System :: OS Independent
Classifier: Topic :: Scientific/Engineering :: Information Analysis
Classifier: Topic :: Software Development :: Libraries :: Python Modules
Requires-Python: >=3.7
License-File: LICENSE
License-File: AUTHORS.rst
Requires-Dist: oauth2-xfel-client (>=6.1)
Requires-Dist: oauthlib
Requires-Dist: pytz
Requires-Dist: requests-oauthlib
Requires-Dist: requests (<2.30)
Provides-Extra: test
Requires-Dist: pycodestyle ; extra == 'test'
Requires-Dist: pytest ; extra == 'test'
Requires-Dist: pytest-cov ; extra == 'test'
Requires-Dist: python-dateutil ; extra == 'test'
Requires-Dist: pytz ; extra == 'test'
